sitemaps/__init__.py
sitemaps/__main__.py
sitemaps/__version__.py
sitemaps/_crawl.py
sitemaps/_main.py
sitemaps/_models.py
sitemaps/_xml.py
sitemaps/py.typed
sitemaps/__pycache__/__init__.cpython-38.pyc
sitemaps/__pycache__/__main__.cpython-38.pyc
sitemaps/__pycache__/__version__.cpython-38.pyc
sitemaps/__pycache__/_crawl.cpython-38.pyc
sitemaps/__pycache__/_main.cpython-38.pyc
sitemaps/__pycache__/_models.cpython-38.pyc
sitemaps/__pycache__/_utils.cpython-38.pyc
sitemaps/__pycache__/_xml.cpython-38.pyc
sitemaps-0.1.0.dist-info/LICENSE
sitemaps-0.1.0.dist-info/METADATA
sitemaps-0.1.0.dist-info/WHEEL
sitemaps-0.1.0.dist-info/top_level.txt
sitemaps-0.1.0.dist-info/RECORD
